hojeongtest/test1.py
hojeongtest/test2.py
hojeongtest-0.0.0.1.dist-info/METADATA
hojeongtest-0.0.0.1.dist-info/WHEEL
hojeongtest-0.0.0.1.dist-info/top_level.txt
hojeongtest-0.0.0.1.dist-info/RECORD
