Metadata-Version: 2.1
Name: hojeongtest
Version: 0.0.0.1
Summary: My First Test Package
Home-page: https://lingua.blog.me/…
Author: Sukjae Choi
Author-email: hojeongi87@gmail.com
License: MIT
Requires-Python: >=3
